WeeLab/__init__.py
WeeLab/const.py
WeeLab/manager.py
WeeLab/connections/__init__.py
WeeLab/connections/base.py
WeeLab/connections/serial.py
WeeLab/connections/visa.py
WeeLab/connections/vxi11conn.py
WeeLab/devices/__init__.py
WeeLab/devices/caen_a7585.py
WeeLab/devices/keithley.py
WeeLab/devices/lecroy9104.py
WeeLab/devices/pilas.py
WeeLab/devices/stage.py
WeeLab/devices/tek_afg.py
WeeLab/interfaces/__init__.py
WeeLab/interfaces/multimetre.py
WeeLab/interfaces/oscilloscope.py
WeeLab/interfaces/power_supply.py
WeeLab/interfaces/wf_generator.py
examples/example.py
tests/__init__.py
tests/conftest.py
tests/test_afg.py
tests/test_caen.py
tests/test_keithley.py
tests/test_lecroy.py
tests/test_pilas.py
tests/test_stage.py
weelab-0.1.3.dist-info/METADATA
weelab-0.1.3.dist-info/WHEEL
weelab-0.1.3.dist-info/top_level.txt
weelab-0.1.3.dist-info/RECORD
