Metadata-Version: 2.4
Name: WeeLab
Version: 0.1.3
Summary: Unified control library for lab equipment (oscilloscopes, power supplies, lasers, etc.)
Author-email: Vsevolod Yeroshenko <vsevolod.yeroshenko@weeroc.com>
License-Expression: MIT
Requires-Python: >=3.8
Requires-Dist: pyserial
Requires-Dist: pyvisa
Requires-Dist: python-vxi11
Requires-Dist: colorama
